pyz3rui/__init__.py
pyz3rui/__main__.py
pyz3rui/cli.py
pyz3rui/macros.py
pyz3rui-1.1.0.dist-info/DESCRIPTION.rst
pyz3rui-1.1.0.dist-info/METADATA
pyz3rui-1.1.0.dist-info/RECORD
pyz3rui-1.1.0.dist-info/WHEEL
pyz3rui-1.1.0.dist-info/entry_points.txt
pyz3rui-1.1.0.dist-info/metadata.json
pyz3rui-1.1.0.dist-info/top_level.txt
