Metadata-Version: 2.0
Name: pyz3rui
Version: 1.1.0
Summary: User interface for pyz3r
Home-page: https://www.github.com/feneg/pyz3rui
Author: Feneg
Author-email: UNKNOWN
License: UNKNOWN
Platform: UNKNOWN
Classifier: Development Status :: 4 - Beta
Classifier: Environment :: Console
Classifier: License :: OSI Approved :: MIT License
Classifier: Programming Language :: Python :: 3.6
Classifier: Topic :: Games/Entertainment
Classifier: Topic :: Utilities
Requires-Dist: pyz3r (>=4.0.0)
